kraken_thing/__init__.py
kraken_thing/kraken_class_observation/__init__.py
kraken_thing/kraken_class_observation/kraken_class_observation.py
kraken_thing/kraken_class_observation/helpers/__init__.py
kraken_thing/kraken_class_observation/helpers/observation_analysis.py
kraken_thing/kraken_class_observation/helpers/observation_comparison.py
kraken_thing/kraken_class_observation/helpers/observation_hash.py
kraken_thing/kraken_class_observation/helpers/observation_json_DEPRECATED.py
kraken_thing/kraken_class_observation/helpers/observation_normalization.py
kraken_thing/kraken_class_observation/helpers/observation_output.py
kraken_thing/kraken_class_observation/helpers/value_conversion.py
kraken_thing/kraken_class_thing/__init__.py
kraken_thing/kraken_class_thing/kraken_class_thing.py
kraken_thing/kraken_class_thing/helpers/__init__.py
kraken_thing/kraken_class_thing/helpers/thing_api_OLD.py
kraken_thing/kraken_class_thing/helpers/thing_comparison.py
kraken_thing/kraken_class_thing/helpers/thing_dot.py
kraken_thing/kraken_class_thing/helpers/thing_json_DEPRECATED.py
kraken_thing/kraken_class_thing/helpers/thing_localization.py
kraken_thing/kraken_class_thing/helpers/thing_names.py
kraken_thing/kraken_class_thing/helpers/thing_output.py
kraken_thing/kraken_class_thing/helpers/thing_summary_record.py
kraken_thing/kraken_class_thing/helpers/thing_test_records.py
kraken_thing/kraken_class_thing/helpers/things_manipulation.py
kraken_thing/kraken_class_thing/kraken_class_thing_actions/__init__.py
kraken_thing/kraken_class_thing/kraken_class_thing_actions/kraken_class_thing_actions.py
kraken_thing/kraken_class_thing/kraken_class_thing_actions/kraken_class_thing_actions_methods.py
kraken_thing/kraken_class_thing/kraken_class_thing_api/__init__.py
kraken_thing/kraken_class_thing/kraken_class_thing_api/kraken_class_thing_api.py
kraken_thing/kraken_class_thing/kraken_class_thing_api/kraken_class_thing_api_methods.py
kraken_thing-0.0.55.dist-info/LICENSE.txt
kraken_thing-0.0.55.dist-info/METADATA
kraken_thing-0.0.55.dist-info/WHEEL
kraken_thing-0.0.55.dist-info/top_level.txt
kraken_thing-0.0.55.dist-info/RECORD
