Metadata-Version: 2.1
Name: kraken-thing
Version: 0.0.55
Summary: Kraken thing
Home-page: https://github.com/tactik8/krakcn_class_thing_v4
Author: Tactik8
Author-email: info@tactik8.com
License: MIT
Classifier: License :: OSI Approved :: MIT License
Classifier: Programming Language :: Python :: 3
Classifier: Programming Language :: Python :: 3.10
License-File: LICENSE.txt
Requires-Dist: python-dateutil
Requires-Dist: sigfig
Requires-Dist: kraken-schema-org
Requires-Dist: requests
Requires-Dist: tabulate
Requires-Dist: flask
Requires-Dist: aiohttp
